{
  "users": [
    {
      "id": "bb463b8b-b76c-4f6a-9726-65ab5730b69b",
      "itemStatus": "OPEN",
      "itemPosition": 0,
      "username": "Enya.Erlei",
      "name": "Brenner, Andrea",
      "email": "Angela.Klauder@hotmail.com",
      "imageUrl": "https://placeimg.com/200/150/people?0"
    },
    {
      "id": "d7bb95b6-5a55-4334-bac1-c606272614e6",
      "itemStatus": "OPEN",
      "itemPosition": 1,
      "username": "Kim_Theele51",
      "name": "Kúhnert, Tobias",
      "email": "Carolin31@yahoo.com",
      "imageUrl": "https://placeimg.com/200/150/people?1"
    },
    {
      "id": "76ade417-7f38-469c-97dc-948650456bad",
      "itemStatus": "OPEN",
      "itemPosition": 2,
      "username": "Mieke.Grosser",
      "name": "Pletsch, Lenny",
      "email": "Maria67@yahoo.com",
      "imageUrl": "https://placeimg.com/200/150/people?2"
    },
    {
      "id": "8d215ce3-2379-4318-a2ae-bf079488242c",
      "itemStatus": "OPEN",
      "itemPosition": 3,
      "username": "Jasmin51",
      "name": "Rath, Paulina",
      "email": "Joscha_Jeorga@yahoo.com",
      "imageUrl": "https://placeimg.com/200/150/people?3"
    },
    {
      "id": "ddb56034-668b-48f0-9ac0-90be246c355d",
      "itemStatus": "OPEN",
      "itemPosition": 4,
      "username": "Alice_Barr",
      "name": "Bönisch, Kerem",
      "email": "Mona_Hensel@gmail.com",
      "imageUrl": "https://placeimg.com/200/150/people?4"
    },
    {
      "id": "3d48dd86-a5c5-4d26-9057-8899840efae5",
      "itemStatus": "OPEN",
      "itemPosition": 5,
      "username": "Johann44",
      "name": "Leibold, Lino",
      "email": "Lucien.Zach@hotmail.com",
      "imageUrl": "https://placeimg.com/200/150/people?5"
    },
    {
      "id": "b98c56ab-d229-4fd5-bd11-603e7e83104d",
      "itemStatus": "OPEN",
      "itemPosition": 6,
      "username": "Sally.Gerhardt",
      "name": "Komoll, Claas",
      "email": "Valentin.Rntsch@hotmail.com",
      "imageUrl": "https://placeimg.com/200/150/people?6"
    },
    {
      "id": "6b4d62cc-c4a4-4fa6-93a7-e8b67270c994",
      "itemStatus": "OPEN",
      "itemPosition": 7,
      "username": "Davin_Stöwer",
      "name": "Schäffel, Viktor",
      "email": "Jack75@yahoo.com",
      "imageUrl": "https://placeimg.com/200/150/people?7"
    },
    {
      "id": "295c71ad-3d9e-4e21-972b-616d861737c5",
      "itemStatus": "OPEN",
      "itemPosition": 8,
      "username": "Tony_Umminger0",
      "name": "Peselman, Arwen",
      "email": "Sandra.Marchewski@yahoo.com",
      "imageUrl": "https://placeimg.com/200/150/people?8"
    },
    {
      "id": "34b46bad-09a7-40ab-a7b1-f8110a9fcc89",
      "itemStatus": "OPEN",
      "itemPosition": 9,
      "username": "Romina69",
      "name": "Kuske, Giulia",
      "email": "Bo.Hentschke51@hotmail.com",
      "imageUrl": "https://placeimg.com/200/150/people?9"
    },
    {
      "id": "465ca607-c295-4adb-a861-f732eae81a75",
      "itemStatus": "OPEN",
      "itemPosition": 10,
      "username": "Alana82",
      "name": "Benzing, Franz",
      "email": "Fabio.Buder@gmail.com",
      "imageUrl": "https://placeimg.com/200/150/people?10"
    },
    {
      "id": "0c4e6054-5fd8-48a8-817c-f6611278f755",
      "itemStatus": "OPEN",
      "itemPosition": 11,
      "username": "Lisanne_Burmeister20",
      "name": "Giesche, Tayler",
      "email": "Joline_Haug@yahoo.com",
      "imageUrl": "https://placeimg.com/200/150/people?11"
    },
    {
      "id": "39fbaadf-0e40-4861-9f23-9553f193a46a",
      "itemStatus": "OPEN",
      "itemPosition": 12,
      "username": "Katja.Göckeritz",
      "name": "Schersing, Ahmad",
      "email": "Nico.Ecker@hotmail.com",
      "imageUrl": "https://placeimg.com/200/150/people?12"
    },
    {
      "id": "289644a6-0dea-40f2-bce0-cb4fcddb5ff6",
      "itemStatus": "OPEN",
      "itemPosition": 13,
      "username": "Ilayda.Streck45",
      "name": "Verzi, Colin",
      "email": "Zoe_Wachtel@gmail.com",
      "imageUrl": "https://placeimg.com/200/150/people?13"
    },
    {
      "id": "1d21d940-8b10-4915-b5ea-558b9a3f94a3",
      "itemStatus": "OPEN",
      "itemPosition": 14,
      "username": "Luiz_Bozsik",
      "name": "Kohle, Baris",
      "email": "Yunus94@hotmail.com",
      "imageUrl": "https://placeimg.com/200/150/people?14"
    },
    {
      "id": "e858a057-eeb3-410b-ae58-df07e0a8e899",
      "itemStatus": "OPEN",
      "itemPosition": 15,
      "username": "Lucienne.Sillah",
      "name": "Holinski, Penelope",
      "email": "Ramon.Sauer@yahoo.com",
      "imageUrl": "https://placeimg.com/200/150/people?15"
    },
    {
      "id": "631f7ea5-4ae4-4734-9656-ecdbb7f86d3b",
      "itemStatus": "OPEN",
      "itemPosition": 16,
      "username": "Eric74",
      "name": "Dietz, Max",
      "email": "Anneke.Montag@gmail.com",
      "imageUrl": "https://placeimg.com/200/150/people?16"
    },
    {
      "id": "19a3ba83-841b-498a-998b-b1ef9131b8c7",
      "itemStatus": "OPEN",
      "itemPosition": 17,
      "username": "Jerome.Erlei46",
      "name": "Stolz, Levke",
      "email": "Kenan17@hotmail.com",
      "imageUrl": "https://placeimg.com/200/150/people?17"
    },
    {
      "id": "f8a8c6b5-3876-4c0a-8011-a56f2754c5b3",
      "itemStatus": "OPEN",
      "itemPosition": 18,
      "username": "Claas.Keutel31",
      "name": "Sonn, Vera",
      "email": "Hennes93@yahoo.com",
      "imageUrl": "https://placeimg.com/200/150/people?18"
    },
    {
      "id": "757e108b-d767-490c-8657-fc9c529c372e",
      "itemStatus": "OPEN",
      "itemPosition": 19,
      "username": "Nelson.Herweg50",
      "name": "Kuhlee, Ludwig",
      "email": "Sophie_Dietrich32@hotmail.com",
      "imageUrl": "https://placeimg.com/200/150/people?19"
    }
  ],
  "groups": [
    {
      "id": "cfdf16aa-96a4-4016-8b42-6920f017ad7e",
      "itemStatus": "OPEN",
      "itemPosition": 0,
      "name": "nihil",
      "description": "ullam",
      "type": "FAMILY",
      "members": [
        "f8a8c6b5-3876-4c0a-8011-a56f2754c5b3"
      ],
      "activity": {
        "date": "2021-03-04T10:04:04.668Z",
        "reps": 6
      }
    },
    {
      "id": "94101e9d-c428-451f-9ed5-67a9f0310a02",
      "itemStatus": "OPEN",
      "itemPosition": 1,
      "name": "impedit",
      "description": "",
      "type": "WORK",
      "members": [],
      "activity": {
        "date": "2021-02-11T21:25:49.214Z",
        "reps": 15
      }
    },
    {
      "id": "677698dd-7a33-46c3-ac21-9f34b65a49fe",
      "itemStatus": "OPEN",
      "itemPosition": 2,
      "name": "ipsa",
      "description": "a",
      "type": "FRIENDS",
      "members": [
        "0c4e6054-5fd8-48a8-817c-f6611278f755",
        "39fbaadf-0e40-4861-9f23-9553f193a46a",
        "6b4d62cc-c4a4-4fa6-93a7-e8b67270c994",
        "b98c56ab-d229-4fd5-bd11-603e7e83104d",
        "bb463b8b-b76c-4f6a-9726-65ab5730b69b",
        "ddb56034-668b-48f0-9ac0-90be246c355d",
        "e858a057-eeb3-410b-ae58-df07e0a8e899"
      ],
      "activity": {
        "date": "2021-12-13T13:34:38.797Z",
        "reps": 6
      }
    },
    {
      "id": "1a0bea80-3497-4f43-8928-90f8e0320cf5",
      "itemStatus": "OPEN",
      "itemPosition": 3,
      "name": "aut",
      "description": "veniam sint",
      "type": "FAMILY",
      "members": [
        "0c4e6054-5fd8-48a8-817c-f6611278f755",
        "0c4e6054-5fd8-48a8-817c-f6611278f755",
        "1d21d940-8b10-4915-b5ea-558b9a3f94a3",
        "295c71ad-3d9e-4e21-972b-616d861737c5"
      ],
      "activity": {
        "date": "2021-10-29T16:06:02.436Z",
        "reps": 10
      }
    },
    {
      "id": "261db2ce-d7f6-4c4c-ae8d-c6d4ef4d5c9a",
      "itemStatus": "OPEN",
      "itemPosition": 4,
      "name": "odio",
      "description": "",
      "type": "WORK",
      "members": [
        "6b4d62cc-c4a4-4fa6-93a7-e8b67270c994",
        "b98c56ab-d229-4fd5-bd11-603e7e83104d",
        "f8a8c6b5-3876-4c0a-8011-a56f2754c5b3"
      ],
      "activity": {
        "date": "2021-04-18T12:44:48.174Z",
        "reps": 9
      }
    }
  ],
  "shops": [
    {
      "id": "bbefc083-7572-40c8-9662-5167205f3646",
      "itemStatus": "OPEN",
      "itemPosition": 0,
      "name": "Lidl",
      "description": "qui illo voluptas",
      "imageUrl": "https://placeimg.com/200/150/arch?0",
      "location": {
        "latitude": "40.6466",
        "longitude": "-161.5946"
      },
      "type": "CHAIN",
      "category": "SUPERMARKET",
      "business": [
        "09:00 - 12:00, 14:00 - 22:00",
        "09:00 - 12:00, 14:00 - 22:00",
        "09:00 - 12:00",
        "09:00 - 12:00, 14:00 - 22:00",
        "09:00 - 12:00, 14:00 - 22:00",
        "09:00 - 12:00, 14:00 - 18:00",
        "closed"
      ]
    },
    {
      "id": "e640d015-ade7-4e0d-adba-bfc35a57cb66",
      "itemStatus": "OPEN",
      "itemPosition": 1,
      "name": "Aldi",
      "description": "occaecati ea ut",
      "imageUrl": "https://placeimg.com/200/150/arch?1",
      "location": {
        "latitude": "40.8944",
        "longitude": "7.6555"
      },
      "type": "CHAIN",
      "category": "SUPERMARKET",
      "business": [
        "09:00 - 12:00, 14:00 - 22:00",
        "09:00 - 12:00, 14:00 - 22:00",
        "09:00 - 12:00",
        "09:00 - 12:00, 14:00 - 22:00",
        "09:00 - 12:00, 14:00 - 22:00",
        "09:00 - 12:00, 14:00 - 18:00",
        "closed"
      ]
    },
    {
      "id": "9f571513-ec78-4fd5-a3e5-157a70dc56e6",
      "itemStatus": "OPEN",
      "itemPosition": 2,
      "name": "Rewe",
      "description": "harum amet officia",
      "imageUrl": "https://placeimg.com/200/150/arch?2",
      "location": {
        "latitude": "4.8407",
        "longitude": "-6.7986"
      },
      "type": "CHAIN",
      "category": "SUPERMARKET",
      "business": [
        "09:00 - 12:00, 14:00 - 22:00",
        "09:00 - 12:00, 14:00 - 22:00",
        "09:00 - 12:00",
        "09:00 - 12:00, 14:00 - 22:00",
        "09:00 - 12:00, 14:00 - 22:00",
        "09:00 - 12:00, 14:00 - 18:00",
        "closed"
      ]
    },
    {
      "id": "3747d5a7-76e8-4298-ba8f-9004803c6cd8",
      "itemStatus": "OPEN",
      "itemPosition": 3,
      "name": "Edeka",
      "description": "sunt voluptas exercitationem",
      "imageUrl": "https://placeimg.com/200/150/arch?3",
      "location": {
        "latitude": "-31.2776",
        "longitude": "32.3688"
      },
      "type": "CHAIN",
      "category": "SUPERMARKET",
      "business": [
        "09:00 - 12:00, 14:00 - 22:00",
        "09:00 - 12:00, 14:00 - 22:00",
        "09:00 - 12:00",
        "09:00 - 12:00, 14:00 - 22:00",
        "09:00 - 12:00, 14:00 - 22:00",
        "09:00 - 12:00, 14:00 - 18:00",
        "closed"
      ]
    },
    {
      "id": "7a0646aa-553b-44ff-b157-408852dae4bb",
      "itemStatus": "OPEN",
      "itemPosition": 4,
      "name": "Obi",
      "description": "quia blanditiis iusto",
      "imageUrl": "https://placeimg.com/200/150/arch?4",
      "location": {
        "latitude": "43.4489",
        "longitude": "-55.0274"
      },
      "type": "CHAIN",
      "category": "HARDWARE",
      "business": [
        "09:00 - 12:00, 14:00 - 22:00",
        "09:00 - 12:00, 14:00 - 22:00",
        "09:00 - 12:00",
        "09:00 - 12:00, 14:00 - 22:00",
        "09:00 - 12:00, 14:00 - 22:00",
        "09:00 - 12:00, 14:00 - 18:00",
        "closed"
      ]
    },
    {
      "id": "6014d187-94aa-4970-8353-779b1cad5627",
      "itemStatus": "OPEN",
      "itemPosition": 5,
      "name": "Bauhaus",
      "description": "eos rerum consequuntur",
      "imageUrl": "https://placeimg.com/200/150/arch?5",
      "location": {
        "latitude": "54.9588",
        "longitude": "-36.5126"
      },
      "type": "CHAIN",
      "category": "HARDWARE",
      "business": [
        "09:00 - 12:00, 14:00 - 22:00",
        "09:00 - 12:00, 14:00 - 22:00",
        "09:00 - 12:00",
        "09:00 - 12:00, 14:00 - 22:00",
        "09:00 - 12:00, 14:00 - 22:00",
        "09:00 - 12:00, 14:00 - 18:00",
        "closed"
      ]
    },
    {
      "id": "11e4b673-096e-4acd-99b6-777da5c1d7df",
      "itemStatus": "OPEN",
      "itemPosition": 6,
      "name": "Hornbach",
      "description": "qui odit id",
      "imageUrl": "https://placeimg.com/200/150/arch?6",
      "location": {
        "latitude": "-19.1000",
        "longitude": "-43.2818"
      },
      "type": "CHAIN",
      "category": "HARDWARE",
      "business": [
        "09:00 - 12:00, 14:00 - 22:00",
        "09:00 - 12:00, 14:00 - 22:00",
        "09:00 - 12:00",
        "09:00 - 12:00, 14:00 - 22:00",
        "09:00 - 12:00, 14:00 - 22:00",
        "09:00 - 12:00, 14:00 - 18:00",
        "closed"
      ]
    },
    {
      "id": "c37062f5-196a-4f0b-a734-2089a244a645",
      "itemStatus": "OPEN",
      "itemPosition": 7,
      "name": "Höffner",
      "description": "quasi nihil omnis",
      "imageUrl": "https://placeimg.com/200/150/arch?7",
      "location": {
        "latitude": "72.3909",
        "longitude": "72.8436"
      },
      "type": "CHAIN",
      "category": "FURNITURE",
      "business": [
        "09:00 - 12:00, 14:00 - 22:00",
        "09:00 - 12:00, 14:00 - 22:00",
        "09:00 - 12:00",
        "09:00 - 12:00, 14:00 - 22:00",
        "09:00 - 12:00, 14:00 - 22:00",
        "09:00 - 12:00, 14:00 - 18:00",
        "closed"
      ]
    },
    {
      "id": "ea1728bd-0bd3-454b-b063-415236674efa",
      "itemStatus": "OPEN",
      "itemPosition": 8,
      "name": "Segmüller",
      "description": "quis possimus nihil",
      "imageUrl": "https://placeimg.com/200/150/arch?8",
      "location": {
        "latitude": "-85.8328",
        "longitude": "74.3328"
      },
      "type": "CHAIN",
      "category": "FURNITURE",
      "business": [
        "09:00 - 12:00, 14:00 - 22:00",
        "09:00 - 12:00, 14:00 - 22:00",
        "09:00 - 12:00",
        "09:00 - 12:00, 14:00 - 22:00",
        "09:00 - 12:00, 14:00 - 22:00",
        "09:00 - 12:00, 14:00 - 18:00",
        "closed"
      ]
    },
    {
      "id": "81746f28-0cf0-4c17-9a04-e64df9b84dfd",
      "itemStatus": "OPEN",
      "itemPosition": 9,
      "name": "XXX Lutz",
      "description": "autem voluptas a",
      "imageUrl": "https://placeimg.com/200/150/arch?9",
      "location": {
        "latitude": "66.3361",
        "longitude": "-162.6640"
      },
      "type": "CHAIN",
      "category": "FURNITURE",
      "business": [
        "09:00 - 12:00, 14:00 - 22:00",
        "09:00 - 12:00, 14:00 - 22:00",
        "09:00 - 12:00",
        "09:00 - 12:00, 14:00 - 22:00",
        "09:00 - 12:00, 14:00 - 22:00",
        "09:00 - 12:00, 14:00 - 18:00",
        "closed"
      ]
    },
    {
      "id": "262ea81b-9f13-43ef-a769-44d732c860e0",
      "itemStatus": "OPEN",
      "itemPosition": 10,
      "name": "Wimmer",
      "description": "molestiae dolorem repellat",
      "imageUrl": "https://placeimg.com/200/150/arch?10",
      "location": {
        "latitude": "22.6891",
        "longitude": "64.6732"
      },
      "type": "CHAIN",
      "category": "BAKERY",
      "business": [
        "09:00 - 12:00, 14:00 - 22:00",
        "09:00 - 12:00, 14:00 - 22:00",
        "09:00 - 12:00",
        "09:00 - 12:00, 14:00 - 22:00",
        "09:00 - 12:00, 14:00 - 22:00",
        "09:00 - 12:00, 14:00 - 18:00",
        "closed"
      ]
    }
  ],
  "products": [
    {
      "id": "729863fc-1d31-45a2-b4ec-c850efd9d0ea",
      "itemStatus": "OPEN",
      "itemPosition": 0,
      "name": "Milk",
      "description": "lactose free",
      "imageUrl": "https://placeimg.com/200/150/tech?0",
      "category": {
        "main": "FOODS",
        "sub": "DAIRY"
      },
      "activity": {
        "date": "Fri Jan 14 2022",
        "reps": 62
      }
    },
    {
      "id": "6642b90b-0a03-418b-8ebf-5fc7ae038bd2",
      "itemStatus": "OPEN",
      "itemPosition": 1,
      "name": "Cheese",
      "description": "Cheddar",
      "imageUrl": "https://placeimg.com/200/150/tech?1",
      "category": {
        "main": "FOODS",
        "sub": "DAIRY"
      },
      "activity": {
        "date": "Sat Jan 15 2022",
        "reps": 89
      }
    },
    {
      "id": "99248dc6-14de-4258-96c3-3ae0ec585e28",
      "itemStatus": "OPEN",
      "itemPosition": 2,
      "name": "Bread",
      "description": "white sliced",
      "imageUrl": "https://placeimg.com/200/150/tech?2",
      "category": {
        "main": "FOODS",
        "sub": "BREKKY"
      },
      "activity": {
        "date": "Sat Jan 15 2022",
        "reps": 11
      }
    },
    {
      "id": "d042cc47-87d5-4d4e-b56d-e9acd5d2fab3",
      "itemStatus": "OPEN",
      "itemPosition": 3,
      "name": "Pees",
      "description": "green",
      "imageUrl": "https://placeimg.com/200/150/tech?3",
      "category": {
        "main": "FOODS",
        "sub": "CANNED_FOOD"
      },
      "activity": {
        "date": "Sat Jan 15 2022",
        "reps": 86
      }
    },
    {
      "id": "ccb79db0-b000-48bc-b3a7-e6d6b198a7ba",
      "itemStatus": "OPEN",
      "itemPosition": 4,
      "name": "Coffee",
      "description": "espresso 9",
      "imageUrl": "https://placeimg.com/200/150/tech?4",
      "category": {
        "main": "FOODS",
        "sub": "BREKKY"
      },
      "activity": {
        "date": "Sat Jan 15 2022",
        "reps": 89
      }
    },
    {
      "id": "a87070cb-0b1f-48e7-b2af-7c356c1aa839",
      "itemStatus": "OPEN",
      "itemPosition": 5,
      "name": "Musli",
      "description": "no fruit",
      "imageUrl": "https://placeimg.com/200/150/tech?5",
      "category": {
        "main": "FOODS",
        "sub": "BREKKY"
      },
      "activity": {
        "date": "Sat Jan 15 2022",
        "reps": 58
      }
    },
    {
      "id": "72fd0e22-4cff-4ef2-8f6c-183e1ee68a8a",
      "itemStatus": "OPEN",
      "itemPosition": 6,
      "name": "Apples",
      "description": "Granny Smith",
      "imageUrl": "https://placeimg.com/200/150/tech?6",
      "category": {
        "main": "FOODS",
        "sub": "FRUIT_VEGETABLE"
      },
      "activity": {
        "date": "Fri Jan 14 2022",
        "reps": 93
      }
    },
    {
      "id": "6502a724-858f-4b74-a658-f5a53213f5f1",
      "itemStatus": "OPEN",
      "itemPosition": 7,
      "name": "Beer",
      "description": "Tegernseer",
      "imageUrl": "https://placeimg.com/200/150/tech?7",
      "category": {
        "main": "FOODS",
        "sub": "BEVERAGES"
      },
      "activity": {
        "date": "Sat Jan 15 2022",
        "reps": 69
      }
    },
    {
      "id": "9e073cc7-e376-45e4-b191-afdce2634abc",
      "itemStatus": "OPEN",
      "itemPosition": 8,
      "name": "Oranges",
      "description": "Sunny Vale",
      "imageUrl": "https://placeimg.com/200/150/tech?8",
      "category": {
        "main": "FOODS",
        "sub": "FRUIT_VEGETABLE"
      },
      "activity": {
        "date": "Sat Jan 15 2022",
        "reps": 19
      }
    },
    {
      "id": "ac72dfe3-b949-49f7-af9b-8dc71103fc7c",
      "itemStatus": "OPEN",
      "itemPosition": 9,
      "name": "Nails",
      "description": "100 x",
      "imageUrl": "https://placeimg.com/200/150/tech?9",
      "category": {
        "main": "HARDWARE",
        "sub": "DIY"
      },
      "activity": {
        "date": "Fri Jan 14 2022",
        "reps": 96
      }
    },
    {
      "id": "5955c862-cb73-4d41-9707-64df2e67c183",
      "itemStatus": "OPEN",
      "itemPosition": 10,
      "name": "Light Bulb",
      "description": "60 W",
      "imageUrl": "https://placeimg.com/200/150/tech?10",
      "category": {
        "main": "HARDWARE",
        "sub": "DIY"
      },
      "activity": {
        "date": "Sat Jan 15 2022",
        "reps": 80
      }
    },
    {
      "id": "6477d51c-77bd-49f1-bb98-d9f94eb405ea",
      "itemStatus": "OPEN",
      "itemPosition": 11,
      "name": "Hammer",
      "description": "rubber",
      "imageUrl": "https://placeimg.com/200/150/tech?11",
      "category": {
        "main": "HARDWARE",
        "sub": "TOOLS"
      },
      "activity": {
        "date": "Sat Jan 15 2022",
        "reps": 86
      }
    },
    {
      "id": "1cb2f58a-3a9a-493a-b2de-b9708a933088",
      "itemStatus": "OPEN",
      "itemPosition": 12,
      "name": "Ladder",
      "description": "foldable",
      "imageUrl": "https://placeimg.com/200/150/tech?12",
      "category": {
        "main": "HARDWARE",
        "sub": "TOOLS"
      },
      "activity": {
        "date": "Sat Jan 15 2022",
        "reps": 12
      }
    },
    {
      "id": "ddbd215a-4b54-4cff-8017-84b83c5e95ee",
      "itemStatus": "OPEN",
      "itemPosition": 13,
      "name": "Wood",
      "description": "Planks",
      "imageUrl": "https://placeimg.com/200/150/tech?13",
      "category": {
        "main": "HARDWARE",
        "sub": "DIY"
      },
      "activity": {
        "date": "Fri Jan 14 2022",
        "reps": 9
      }
    },
    {
      "id": "b238468d-cf90-4809-bc58-aeafde3c5386",
      "itemStatus": "OPEN",
      "itemPosition": 14,
      "name": "Paper",
      "description": "A4",
      "imageUrl": "https://placeimg.com/200/150/tech?14",
      "category": {
        "main": "SUPPLIES",
        "sub": "OFFICE"
      },
      "activity": {
        "date": "Sat Jan 15 2022",
        "reps": 68
      }
    },
    {
      "id": "244a55cc-319c-4d9d-9961-9f8afac6882c",
      "itemStatus": "OPEN",
      "itemPosition": 15,
      "name": "Stapler",
      "description": "large",
      "imageUrl": "https://placeimg.com/200/150/tech?15",
      "category": {
        "main": "SUPPLIES",
        "sub": "OFFICE"
      },
      "activity": {
        "date": "Fri Jan 14 2022",
        "reps": 61
      }
    },
    {
      "id": "e038a0e7-3f35-4ddd-a5f4-925f2d1ec801",
      "itemStatus": "OPEN",
      "itemPosition": 16,
      "name": "Pen",
      "description": "blue",
      "imageUrl": "https://placeimg.com/200/150/tech?16",
      "category": {
        "main": "SUPPLIES",
        "sub": "OFFICE"
      },
      "activity": {
        "date": "Fri Jan 14 2022",
        "reps": 38
      }
    },
    {
      "id": "4095cebf-0df2-416f-b133-aa7955178f59",
      "itemStatus": "OPEN",
      "itemPosition": 17,
      "name": "Stamp",
      "description": "60 p",
      "imageUrl": "https://placeimg.com/200/150/tech?17",
      "category": {
        "main": "SUPPLIES",
        "sub": "POSTAL"
      },
      "activity": {
        "date": "Fri Jan 14 2022",
        "reps": 16
      }
    },
    {
      "id": "684d6b88-07dd-4e38-b45f-c61b0b56e36f",
      "itemStatus": "OPEN",
      "itemPosition": 18,
      "name": "Envelope",
      "description": "100 x",
      "imageUrl": "https://placeimg.com/200/150/tech?18",
      "category": {
        "main": "SUPPLIES",
        "sub": "POSTAL"
      },
      "activity": {
        "date": "Fri Jan 14 2022",
        "reps": 49
      }
    },
    {
      "id": "c1679354-1dc5-4616-bad5-f74bac1fb06f",
      "itemStatus": "OPEN",
      "itemPosition": 19,
      "name": "Suit",
      "description": "blue",
      "imageUrl": "https://placeimg.com/200/150/tech?19",
      "category": {
        "main": "CLOTHING",
        "sub": "BUSINESS"
      },
      "activity": {
        "date": "Sat Jan 15 2022",
        "reps": 18
      }
    },
    {
      "id": "e24ef684-59a0-43f3-83bf-979ca76969ef",
      "itemStatus": "OPEN",
      "itemPosition": 20,
      "name": "Shirt",
      "description": "white",
      "imageUrl": "https://placeimg.com/200/150/tech?20",
      "category": {
        "main": "CLOTHING",
        "sub": "BUSINESS"
      },
      "activity": {
        "date": "Fri Jan 14 2022",
        "reps": 12
      }
    },
    {
      "id": "fa33b043-f776-4bc3-8d16-f88d9d68a9dc",
      "itemStatus": "OPEN",
      "itemPosition": 21,
      "name": "T-Shirt",
      "description": "XXL",
      "imageUrl": "https://placeimg.com/200/150/tech?21",
      "category": {
        "main": "CLOTHING",
        "sub": "LEISURE"
      },
      "activity": {
        "date": "Fri Jan 14 2022",
        "reps": 87
      }
    },
    {
      "id": "a4f7b6d4-09a2-4a51-8dd9-a1e90733e095",
      "itemStatus": "OPEN",
      "itemPosition": 22,
      "name": "Shorts",
      "description": "swimming",
      "imageUrl": "https://placeimg.com/200/150/tech?22",
      "category": {
        "main": "CLOTHING",
        "sub": "LEISURE"
      },
      "activity": {
        "date": "Fri Jan 14 2022",
        "reps": 52
      }
    },
    {
      "id": "e955246c-9c9b-461f-808e-b6ed5265bfa9",
      "itemStatus": "OPEN",
      "itemPosition": 23,
      "name": "Boots",
      "description": "black",
      "imageUrl": "https://placeimg.com/200/150/tech?23",
      "category": {
        "main": "CLOTHING",
        "sub": "SHOES"
      },
      "activity": {
        "date": "Fri Jan 14 2022",
        "reps": 32
      }
    }
  ],
  "lists": [
    {
      "id": "2d7bdec2-882b-461b-8520-59ab2ba245c6",
      "itemStatus": "OPEN",
      "itemPosition": 4,
      "name": "Groceries",
      "description": "quis qui doloribus",
      "items": [
        {
          "id": "6477d51c-77bd-49f1-bb98-d9f94eb405ea",
          "status": "DONE",
          "listPosition": 3
        },
        {
          "id": "729863fc-1d31-45a2-b4ec-c850efd9d0ea",
          "status": "DONE",
          "listPosition": 1
        },
        {
          "id": "9e073cc7-e376-45e4-b191-afdce2634abc",
          "status": "DONE",
          "listPosition": 9
        },
        {
          "id": "d042cc47-87d5-4d4e-b56d-e9acd5d2fab3",
          "status": "IN_PROGRESS",
          "listPosition": 4
        },
        {
          "id": "e955246c-9c9b-461f-808e-b6ed5265bfa9",
          "status": "IN_PROGRESS",
          "listPosition": 5
        }
      ],
      "members": [
        "6b4d62cc-c4a4-4fa6-93a7-e8b67270c994",
        "b98c56ab-d229-4fd5-bd11-603e7e83104d",
        "f8a8c6b5-3876-4c0a-8011-a56f2754c5b3"
      ],
      "lifecycle": {
        "status": "IN_PROGRESS",
        "completion": 60
      }
    },
    {
      "id": "66e11618-0b09-406d-a897-faddaee1f83f",
      "itemStatus": "OPEN",
      "itemPosition": 1,
      "name": "Xmas party",
      "description": "accusamus dicta asperiores",
      "items": [
        {
          "id": "1cb2f58a-3a9a-493a-b2de-b9708a933088",
          "status": "DONE",
          "listPosition": 4
        },
        {
          "id": "244a55cc-319c-4d9d-9961-9f8afac6882c",
          "status": "DONE",
          "listPosition": 2
        },
        {
          "id": "244a55cc-319c-4d9d-9961-9f8afac6882c",
          "status": "OPEN",
          "listPosition": 2
        },
        {
          "id": "5955c862-cb73-4d41-9707-64df2e67c183",
          "status": "DONE",
          "listPosition": 2
        },
        {
          "id": "6502a724-858f-4b74-a658-f5a53213f5f1",
          "status": "DONE",
          "listPosition": 8
        },
        {
          "id": "6642b90b-0a03-418b-8ebf-5fc7ae038bd2",
          "status": "IN_PROGRESS",
          "listPosition": 2
        },
        {
          "id": "72fd0e22-4cff-4ef2-8f6c-183e1ee68a8a",
          "status": "DONE",
          "listPosition": 7
        },
        {
          "id": "99248dc6-14de-4258-96c3-3ae0ec585e28",
          "status": "DONE",
          "listPosition": 3
        },
        {
          "id": "a87070cb-0b1f-48e7-b2af-7c356c1aa839",
          "status": "OPEN",
          "listPosition": 6
        },
        {
          "id": "b238468d-cf90-4809-bc58-aeafde3c5386",
          "status": "OPEN",
          "listPosition": 1
        },
        {
          "id": "c1679354-1dc5-4616-bad5-f74bac1fb06f",
          "status": "DONE",
          "listPosition": 1
        },
        {
          "id": "ccb79db0-b000-48bc-b3a7-e6d6b198a7ba",
          "status": "OPEN",
          "listPosition": 5
        },
        {
          "id": "e038a0e7-3f35-4ddd-a5f4-925f2d1ec801",
          "status": "IN_PROGRESS",
          "listPosition": 3
        },
        {
          "id": "e955246c-9c9b-461f-808e-b6ed5265bfa9",
          "status": "OPEN",
          "listPosition": 5
        },
        {
          "id": "e955246c-9c9b-461f-808e-b6ed5265bfa9",
          "status": "IN_PROGRESS",
          "listPosition": 5
        }
      ],
      "members": [
        "6b4d62cc-c4a4-4fa6-93a7-e8b67270c994",
        "b98c56ab-d229-4fd5-bd11-603e7e83104d",
        "f8a8c6b5-3876-4c0a-8011-a56f2754c5b3"
      ],
      "lifecycle": {
        "status": "IN_PROGRESS",
        "completion": 47
      }
    },
    {
      "id": "b0e30fca-1ce6-4972-902d-b26f814d36ad",
      "itemStatus": "OPEN",
      "itemPosition": 2,
      "name": "After work event",
      "description": "ab molestiae consequuntur",
      "items": [
        {
          "id": "244a55cc-319c-4d9d-9961-9f8afac6882c",
          "status": "IN_PROGRESS",
          "listPosition": 2
        },
        {
          "id": "4095cebf-0df2-416f-b133-aa7955178f59",
          "status": "DONE",
          "listPosition": 4
        },
        {
          "id": "4095cebf-0df2-416f-b133-aa7955178f59",
          "status": "OPEN",
          "listPosition": 4
        },
        {
          "id": "6477d51c-77bd-49f1-bb98-d9f94eb405ea",
          "status": "IN_PROGRESS",
          "listPosition": 3
        },
        {
          "id": "684d6b88-07dd-4e38-b45f-c61b0b56e36f",
          "status": "IN_PROGRESS",
          "listPosition": 5
        },
        {
          "id": "684d6b88-07dd-4e38-b45f-c61b0b56e36f",
          "status": "DONE",
          "listPosition": 5
        },
        {
          "id": "729863fc-1d31-45a2-b4ec-c850efd9d0ea",
          "status": "DONE",
          "listPosition": 1
        },
        {
          "id": "729863fc-1d31-45a2-b4ec-c850efd9d0ea",
          "status": "DONE",
          "listPosition": 1
        },
        {
          "id": "99248dc6-14de-4258-96c3-3ae0ec585e28",
          "status": "DONE",
          "listPosition": 3
        },
        {
          "id": "a87070cb-0b1f-48e7-b2af-7c356c1aa839",
          "status": "IN_PROGRESS",
          "listPosition": 6
        },
        {
          "id": "a87070cb-0b1f-48e7-b2af-7c356c1aa839",
          "status": "DONE",
          "listPosition": 6
        },
        {
          "id": "ac72dfe3-b949-49f7-af9b-8dc71103fc7c",
          "status": "IN_PROGRESS",
          "listPosition": 1
        },
        {
          "id": "d042cc47-87d5-4d4e-b56d-e9acd5d2fab3",
          "status": "DONE",
          "listPosition": 4
        },
        {
          "id": "ddbd215a-4b54-4cff-8017-84b83c5e95ee",
          "status": "DONE",
          "listPosition": 5
        },
        {
          "id": "e24ef684-59a0-43f3-83bf-979ca76969ef",
          "status": "DONE",
          "listPosition": 2
        },
        {
          "id": "e24ef684-59a0-43f3-83bf-979ca76969ef",
          "status": "IN_PROGRESS",
          "listPosition": 2
        }
      ],
      "members": [
        "6b4d62cc-c4a4-4fa6-93a7-e8b67270c994",
        "b98c56ab-d229-4fd5-bd11-603e7e83104d",
        "f8a8c6b5-3876-4c0a-8011-a56f2754c5b3"
      ],
      "lifecycle": {
        "status": "IN_PROGRESS",
        "completion": 56
      }
    },
    {
      "id": "7c8d374b-c540-4d3d-8154-780303a81811",
      "itemStatus": "OPEN",
      "itemPosition": 3,
      "name": "Road trip",
      "description": "sit facilis impedit",
      "items": [],
      "members": [
        "6b4d62cc-c4a4-4fa6-93a7-e8b67270c994",
        "b98c56ab-d229-4fd5-bd11-603e7e83104d",
        "f8a8c6b5-3876-4c0a-8011-a56f2754c5b3"
      ],
      "lifecycle": {
        "status": "DONE",
        "completion": 100
      }
    },
    {
      "id": "71bdf347-1719-4331-b044-42d0651d74ab",
      "itemStatus": "OPEN",
      "itemPosition": 4,
      "name": "Redecoration",
      "description": "labore aut non",
      "items": [
        {
          "id": "6642b90b-0a03-418b-8ebf-5fc7ae038bd2",
          "status": "OPEN",
          "listPosition": 2
        },
        {
          "id": "729863fc-1d31-45a2-b4ec-c850efd9d0ea",
          "status": "IN_PROGRESS",
          "listPosition": 1
        },
        {
          "id": "a87070cb-0b1f-48e7-b2af-7c356c1aa839",
          "status": "DONE",
          "listPosition": 6
        },
        {
          "id": "ac72dfe3-b949-49f7-af9b-8dc71103fc7c",
          "status": "IN_PROGRESS",
          "listPosition": 1
        },
        {
          "id": "b238468d-cf90-4809-bc58-aeafde3c5386",
          "status": "DONE",
          "listPosition": 1
        },
        {
          "id": "b238468d-cf90-4809-bc58-aeafde3c5386",
          "status": "DONE",
          "listPosition": 1
        },
        {
          "id": "e038a0e7-3f35-4ddd-a5f4-925f2d1ec801",
          "status": "OPEN",
          "listPosition": 3
        },
        {
          "id": "e955246c-9c9b-461f-808e-b6ed5265bfa9",
          "status": "IN_PROGRESS",
          "listPosition": 5
        },
        {
          "id": "fa33b043-f776-4bc3-8d16-f88d9d68a9dc",
          "status": "IN_PROGRESS",
          "listPosition": 3
        },
        {
          "id": "fa33b043-f776-4bc3-8d16-f88d9d68a9dc",
          "status": "DONE",
          "listPosition": 3
        }
      ],
      "members": [
        "6b4d62cc-c4a4-4fa6-93a7-e8b67270c994",
        "b98c56ab-d229-4fd5-bd11-603e7e83104d",
        "f8a8c6b5-3876-4c0a-8011-a56f2754c5b3"
      ],
      "lifecycle": {
        "status": "IN_PROGRESS",
        "completion": 40
      }
    }
  ]
}